Metadata-Version: 2.1
Name: buildmc
Version: 0.6.0
Summary: Pure-Python build ochestrator using CMake or Meson to configure+build via a single simple command.
Home-page: https://github.com/scivision/buildmc
Author: Michael Hirsch, Ph.D.
Author-email: scivision@users.noreply.github.com
License: UNKNOWN
Keywords: cmake,meson
Platform: UNKNOWN
Classifier: Development Status :: 4 - Beta
Classifier: Environment :: Console
Classifier: Intended Audience :: Developers
Classifier: License :: OSI Approved :: MIT License
Classifier: Operating System :: OS Independent
Classifier: Programming Language :: Python :: 3.6
Classifier: Programming Language :: Python :: 3.7
Classifier: Programming Language :: Python :: 3.8
Classifier: Topic :: Software Development :: Build Tools
Requires-Python: >= 3.6
Provides-Extra: tests
Provides-Extra: cov
